top/__init__.py
top/api/__init__.py
top/api/base.py
top/api/rest/AppipGetRequest.py
top/api/rest/FilesGetRequest.py
top/api/rest/HttpdnsGetRequest.py
top/api/rest/KfcKeywordSearchRequest.py
top/api/rest/OpenuidChangeRequest.py
top/api/rest/OpenuidGetBymixnickRequest.py
top/api/rest/OpenuidGetBytradeRequest.py
top/api/rest/OpenuidGetRequest.py
top/api/rest/TbkCouponGetRequest.py
top/api/rest/TbkDgMaterialOptionalRequest.py
top/api/rest/TbkItemInfoGetRequest.py
top/api/rest/TbkShopGetRequest.py
top/api/rest/TbkTpwdCreateRequest.py
top/api/rest/TimeGetRequest.py
top/api/rest/TopAuthTokenCreateRequest.py
top/api/rest/TopAuthTokenRefreshRequest.py
top/api/rest/TopIpoutGetRequest.py
top/api/rest/TopSdkFeedbackUploadRequest.py
top/api/rest/TopSecretGetRequest.py
top/api/rest/TopSecretRegisterRequest.py
top/api/rest/__init__.py
top_zx-0.1.1.dist-info/LICENSE
top_zx-0.1.1.dist-info/METADATA
top_zx-0.1.1.dist-info/WHEEL
top_zx-0.1.1.dist-info/top_level.txt
top_zx-0.1.1.dist-info/RECORD
