Metadata-Version: 2.1
Name: top-zx
Version: 0.1.1
Summary: Taobao SDK for taobao spreader
Home-page: https://github.com/lv-cha/tk_sdk
Author: lvcha
Author-email: zhaoxicn@foxmail.com
License: Mulan
Platform: UNKNOWN
Classifier: Programming Language :: Python :: 3
Classifier: Operating System :: OS Independent
Requires-Python: >=3.4
